[{"arguments":["clang","-Wno-documentation-unknown-command","-Wno-unknown-warning-option","-Wno-unknown-pragmas","-nostdinc","-nostdinc++","-g","-std=gnu++1z","-Wall","-Wextra","-Wextra","-fexceptions","-mthreads","-fsyntax-only","-m64","--target=x86_64-w64-mingw32","-DUNICODE","-D_UNICODE","-DWIN32","-DMINGW_HAS_SECURE_API","-DQT_DEPRECATED_WARNINGS","-DQT_QML_DEBUG","-DQT_CHARTS_LIB","-DQT_OPENGLWIDGETS_LIB","-DQT_WIDGETS_LIB","-DQT_OPENGL_LIB","-DQT_GUI_LIB","-DQT_SERIALPORT_LIB","-DQT_NETWORK_LIB","-DQT_CORE5COMPAT_LIB","-DQT_CORE_LIB","-DQT_NEEDS_QMAIN","-DQ_CREATOR_RUN","-DQT_ANNOTATE_FUNCTION(x)=__attribute__((annotate(#x)))","-IC:\\QT_new\\Tools\\QtCreator\\share\\qtcreator\\cplusplus\\wrappedMingwHeaders","-IC:\\QT_new\\Tools\\QtCreator\\share\\qtcreator\\cplusplus\\wrappedQtHeaders","-IC:\\QT_new\\Tools\\QtCreator\\share\\qtcreator\\cplusplus\\wrappedQtHeaders\\QtCore","-IC:\\Users\\Chang\\Desktop\\灵巧手\\产品版\\上位机\\Qt\\Soft_Hand","-IC:\\QT_new\\6.5.3\\mingw_64\\include","-IC:\\QT_new\\6.5.3\\mingw_64\\include\\QtCharts","-IC:\\QT_new\\6.5.3\\mingw_64\\include\\QtOpenGLWidgets","-IC:\\QT_new\\6.5.3\\mingw_64\\include\\QtWidgets","-IC:\\QT_new\\6.5.3\\mingw_64\\include\\QtOpenGL","-IC:\\QT_new\\6.5.3\\mingw_64\\include\\QtGui","-IC:\\QT_new\\6.5.3\\mingw_64\\include\\QtSerialPort","-IC:\\QT_new\\6.5.3\\mingw_64\\include\\QtNetwork","-IC:\\QT_new\\6.5.3\\mingw_64\\include\\QtCore5Compat","-IC:\\QT_new\\6.5.3\\mingw_64\\include\\QtCore","-IC:\\Users\\Chang\\Desktop\\灵巧手\\产品版\\上位机\\Qt\\Soft_Hand\\build\\Desktop_Qt_6_5_3_MinGW_64_bit-Debug\\debug","-IC:\\Users\\Chang\\Desktop\\灵巧手\\产品版\\上位机\\Qt\\Soft_Hand\\build\\Desktop_Qt_6_5_3_MinGW_64_bit-Debug","-IC:\\QT_new\\6.5.3\\mingw_64\\mkspecs\\win32-g++","-isystem","C:\\QT_new\\Tools\\mingw1120_64\\lib\\gcc\\x86_64-w64-mingw32\\11.2.0\\include\\c++","-isystem","C:\\QT_new\\Tools\\mingw1120_64\\lib\\gcc\\x86_64-w64-mingw32\\11.2.0\\include\\c++\\x86_64-w64-mingw32","-isystem","C:\\QT_new\\Tools\\mingw1120_64\\lib\\gcc\\x86_64-w64-mingw32\\11.2.0\\include\\c++\\backward","-isystem","C:\\QT_new\\Tools\\QtCreator\\bin\\clang\\lib\\clang\\18\\include","-isystem","C:\\QT_new\\Tools\\mingw1120_64\\x86_64-w64-mingw32\\include","-fmessage-length=0","-fdiagnostics-show-note-include-stack","-fretain-comments-from-system-headers","-fmacro-backtrace-limit=0","-ferror-limit=1000","-x","c++","C:\\Users\\Chang\\Desktop\\灵巧手\\产品版\\上位机\\Qt\\Soft_Hand\\main.cpp"],"directory":"C:/Users/Chang/Desktop/灵巧手/产品版/上位机/Qt/Soft_Hand/build/Desktop_Qt_6_5_3_MinGW_64_bit-Debug/.qtc_clangd","file":"C:/Users/Chang/Desktop/灵巧手/产品版/上位机/Qt/Soft_Hand/main.cpp"},{"arguments":["clang","-Wno-documentation-unknown-command","-Wno-unknown-warning-option","-Wno-unknown-pragmas","-nostdinc","-nostdinc++","-g","-std=gnu++1z","-Wall","-Wextra","-Wextra","-fexceptions","-mthreads","-fsyntax-only","-m64","--target=x86_64-w64-mingw32","-DUNICODE","-D_UNICODE","-DWIN32","-DMINGW_HAS_SECURE_API","-DQT_DEPRECATED_WARNINGS","-DQT_QML_DEBUG","-DQT_CHARTS_LIB","-DQT_OPENGLWIDGETS_LIB","-DQT_WIDGETS_LIB","-DQT_OPENGL_LIB","-DQT_GUI_LIB","-DQT_SERIALPORT_LIB","-DQT_NETWORK_LIB","-DQT_CORE5COMPAT_LIB","-DQT_CORE_LIB","-DQT_NEEDS_QMAIN","-DQ_CREATOR_RUN","-DQT_ANNOTATE_FUNCTION(x)=__attribute__((annotate(#x)))","-IC:\\QT_new\\Tools\\QtCreator\\share\\qtcreator\\cplusplus\\wrappedMingwHeaders","-IC:\\QT_new\\Tools\\QtCreator\\share\\qtcreator\\cplusplus\\wrappedQtHeaders","-IC:\\QT_new\\Tools\\QtCreator\\share\\qtcreator\\cplusplus\\wrappedQtHeaders\\QtCore","-IC:\\Users\\Chang\\Desktop\\灵巧手\\产品版\\上位机\\Qt\\Soft_Hand","-IC:\\QT_new\\6.5.3\\mingw_64\\include","-IC:\\QT_new\\6.5.3\\mingw_64\\include\\QtCharts","-IC:\\QT_new\\6.5.3\\mingw_64\\include\\QtOpenGLWidgets","-IC:\\QT_new\\6.5.3\\mingw_64\\include\\QtWidgets","-IC:\\QT_new\\6.5.3\\mingw_64\\include\\QtOpenGL","-IC:\\QT_new\\6.5.3\\mingw_64\\include\\QtGui","-IC:\\QT_new\\6.5.3\\mingw_64\\include\\QtSerialPort","-IC:\\QT_new\\6.5.3\\mingw_64\\include\\QtNetwork","-IC:\\QT_new\\6.5.3\\mingw_64\\include\\QtCore5Compat","-IC:\\QT_new\\6.5.3\\mingw_64\\include\\QtCore","-IC:\\Users\\Chang\\Desktop\\灵巧手\\产品版\\上位机\\Qt\\Soft_Hand\\build\\Desktop_Qt_6_5_3_MinGW_64_bit-Debug\\debug","-IC:\\Users\\Chang\\Desktop\\灵巧手\\产品版\\上位机\\Qt\\Soft_Hand\\build\\Desktop_Qt_6_5_3_MinGW_64_bit-Debug","-IC:\\QT_new\\6.5.3\\mingw_64\\mkspecs\\win32-g++","-isystem","C:\\QT_new\\Tools\\mingw1120_64\\lib\\gcc\\x86_64-w64-mingw32\\11.2.0\\include\\c++","-isystem","C:\\QT_new\\Tools\\mingw1120_64\\lib\\gcc\\x86_64-w64-mingw32\\11.2.0\\include\\c++\\x86_64-w64-mingw32","-isystem","C:\\QT_new\\Tools\\mingw1120_64\\lib\\gcc\\x86_64-w64-mingw32\\11.2.0\\include\\c++\\backward","-isystem","C:\\QT_new\\Tools\\QtCreator\\bin\\clang\\lib\\clang\\18\\include","-isystem","C:\\QT_new\\Tools\\mingw1120_64\\x86_64-w64-mingw32\\include","-fmessage-length=0","-fdiagnostics-show-note-include-stack","-fretain-comments-from-system-headers","-fmacro-backtrace-limit=0","-ferror-limit=1000","-x","c++","C:\\Users\\Chang\\Desktop\\灵巧手\\产品版\\上位机\\Qt\\Soft_Hand\\mainwindow.cpp"],"directory":"C:/Users/Chang/Desktop/灵巧手/产品版/上位机/Qt/Soft_Hand/build/Desktop_Qt_6_5_3_MinGW_64_bit-Debug/.qtc_clangd","file":"C:/Users/Chang/Desktop/灵巧手/产品版/上位机/Qt/Soft_Hand/mainwindow.cpp"},{"arguments":["clang","-Wno-documentation-unknown-command","-Wno-unknown-warning-option","-Wno-unknown-pragmas","-nostdinc","-nostdinc++","-g","-std=gnu++1z","-Wall","-Wextra","-Wextra","-fexceptions","-mthreads","-fsyntax-only","-m64","--target=x86_64-w64-mingw32","-DUNICODE","-D_UNICODE","-DWIN32","-DMINGW_HAS_SECURE_API","-DQT_DEPRECATED_WARNINGS","-DQT_QML_DEBUG","-DQT_CHARTS_LIB","-DQT_OPENGLWIDGETS_LIB","-DQT_WIDGETS_LIB","-DQT_OPENGL_LIB","-DQT_GUI_LIB","-DQT_SERIALPORT_LIB","-DQT_NETWORK_LIB","-DQT_CORE5COMPAT_LIB","-DQT_CORE_LIB","-DQT_NEEDS_QMAIN","-DQ_CREATOR_RUN","-DQT_ANNOTATE_FUNCTION(x)=__attribute__((annotate(#x)))","-IC:\\QT_new\\Tools\\QtCreator\\share\\qtcreator\\cplusplus\\wrappedMingwHeaders","-IC:\\QT_new\\Tools\\QtCreator\\share\\qtcreator\\cplusplus\\wrappedQtHeaders","-IC:\\QT_new\\Tools\\QtCreator\\share\\qtcreator\\cplusplus\\wrappedQtHeaders\\QtCore","-IC:\\Users\\Chang\\Desktop\\灵巧手\\产品版\\上位机\\Qt\\Soft_Hand","-IC:\\QT_new\\6.5.3\\mingw_64\\include","-IC:\\QT_new\\6.5.3\\mingw_64\\include\\QtCharts","-IC:\\QT_new\\6.5.3\\mingw_64\\include\\QtOpenGLWidgets","-IC:\\QT_new\\6.5.3\\mingw_64\\include\\QtWidgets","-IC:\\QT_new\\6.5.3\\mingw_64\\include\\QtOpenGL","-IC:\\QT_new\\6.5.3\\mingw_64\\include\\QtGui","-IC:\\QT_new\\6.5.3\\mingw_64\\include\\QtSerialPort","-IC:\\QT_new\\6.5.3\\mingw_64\\include\\QtNetwork","-IC:\\QT_new\\6.5.3\\mingw_64\\include\\QtCore5Compat","-IC:\\QT_new\\6.5.3\\mingw_64\\include\\QtCore","-IC:\\Users\\Chang\\Desktop\\灵巧手\\产品版\\上位机\\Qt\\Soft_Hand\\build\\Desktop_Qt_6_5_3_MinGW_64_bit-Debug\\debug","-IC:\\Users\\Chang\\Desktop\\灵巧手\\产品版\\上位机\\Qt\\Soft_Hand\\build\\Desktop_Qt_6_5_3_MinGW_64_bit-Debug","-IC:\\QT_new\\6.5.3\\mingw_64\\mkspecs\\win32-g++","-isystem","C:\\QT_new\\Tools\\mingw1120_64\\lib\\gcc\\x86_64-w64-mingw32\\11.2.0\\include\\c++","-isystem","C:\\QT_new\\Tools\\mingw1120_64\\lib\\gcc\\x86_64-w64-mingw32\\11.2.0\\include\\c++\\x86_64-w64-mingw32","-isystem","C:\\QT_new\\Tools\\mingw1120_64\\lib\\gcc\\x86_64-w64-mingw32\\11.2.0\\include\\c++\\backward","-isystem","C:\\QT_new\\Tools\\QtCreator\\bin\\clang\\lib\\clang\\18\\include","-isystem","C:\\QT_new\\Tools\\mingw1120_64\\x86_64-w64-mingw32\\include","-fmessage-length=0","-fdiagnostics-show-note-include-stack","-fretain-comments-from-system-headers","-fmacro-backtrace-limit=0","-ferror-limit=1000","-x","c++-header","C:\\Users\\Chang\\Desktop\\灵巧手\\产品版\\上位机\\Qt\\Soft_Hand\\mainwindow.h"],"directory":"C:/Users/Chang/Desktop/灵巧手/产品版/上位机/Qt/Soft_Hand/build/Desktop_Qt_6_5_3_MinGW_64_bit-Debug/.qtc_clangd","file":"C:/Users/Chang/Desktop/灵巧手/产品版/上位机/Qt/Soft_Hand/mainwindow.h"},{"arguments":["clang","-Wno-documentation-unknown-command","-Wno-unknown-warning-option","-Wno-unknown-pragmas","-nostdinc","-nostdinc++","-g","-std=gnu++1z","-Wall","-Wextra","-Wextra","-fexceptions","-mthreads","-fsyntax-only","-m64","--target=x86_64-w64-mingw32","-DUNICODE","-D_UNICODE","-DWIN32","-DMINGW_HAS_SECURE_API","-DQT_DEPRECATED_WARNINGS","-DQT_QML_DEBUG","-DQT_CHARTS_LIB","-DQT_OPENGLWIDGETS_LIB","-DQT_WIDGETS_LIB","-DQT_OPENGL_LIB","-DQT_GUI_LIB","-DQT_SERIALPORT_LIB","-DQT_NETWORK_LIB","-DQT_CORE5COMPAT_LIB","-DQT_CORE_LIB","-DQT_NEEDS_QMAIN","-DQ_CREATOR_RUN","-DQT_ANNOTATE_FUNCTION(x)=__attribute__((annotate(#x)))","-IC:\\QT_new\\Tools\\QtCreator\\share\\qtcreator\\cplusplus\\wrappedMingwHeaders","-IC:\\QT_new\\Tools\\QtCreator\\share\\qtcreator\\cplusplus\\wrappedQtHeaders","-IC:\\QT_new\\Tools\\QtCreator\\share\\qtcreator\\cplusplus\\wrappedQtHeaders\\QtCore","-IC:\\Users\\Chang\\Desktop\\灵巧手\\产品版\\上位机\\Qt\\Soft_Hand","-IC:\\QT_new\\6.5.3\\mingw_64\\include","-IC:\\QT_new\\6.5.3\\mingw_64\\include\\QtCharts","-IC:\\QT_new\\6.5.3\\mingw_64\\include\\QtOpenGLWidgets","-IC:\\QT_new\\6.5.3\\mingw_64\\include\\QtWidgets","-IC:\\QT_new\\6.5.3\\mingw_64\\include\\QtOpenGL","-IC:\\QT_new\\6.5.3\\mingw_64\\include\\QtGui","-IC:\\QT_new\\6.5.3\\mingw_64\\include\\QtSerialPort","-IC:\\QT_new\\6.5.3\\mingw_64\\include\\QtNetwork","-IC:\\QT_new\\6.5.3\\mingw_64\\include\\QtCore5Compat","-IC:\\QT_new\\6.5.3\\mingw_64\\include\\QtCore","-IC:\\Users\\Chang\\Desktop\\灵巧手\\产品版\\上位机\\Qt\\Soft_Hand\\build\\Desktop_Qt_6_5_3_MinGW_64_bit-Debug\\debug","-IC:\\Users\\Chang\\Desktop\\灵巧手\\产品版\\上位机\\Qt\\Soft_Hand\\build\\Desktop_Qt_6_5_3_MinGW_64_bit-Debug","-IC:\\QT_new\\6.5.3\\mingw_64\\mkspecs\\win32-g++","-isystem","C:\\QT_new\\Tools\\mingw1120_64\\lib\\gcc\\x86_64-w64-mingw32\\11.2.0\\include\\c++","-isystem","C:\\QT_new\\Tools\\mingw1120_64\\lib\\gcc\\x86_64-w64-mingw32\\11.2.0\\include\\c++\\x86_64-w64-mingw32","-isystem","C:\\QT_new\\Tools\\mingw1120_64\\lib\\gcc\\x86_64-w64-mingw32\\11.2.0\\include\\c++\\backward","-isystem","C:\\QT_new\\Tools\\QtCreator\\bin\\clang\\lib\\clang\\18\\include","-isystem","C:\\QT_new\\Tools\\mingw1120_64\\x86_64-w64-mingw32\\include","-fmessage-length=0","-fdiagnostics-show-note-include-stack","-fretain-comments-from-system-headers","-fmacro-backtrace-limit=0","-ferror-limit=1000","-x","c++-header","C:\\Users\\Chang\\Desktop\\灵巧手\\产品版\\上位机\\Qt\\Soft_Hand\\build\\Desktop_Qt_6_5_3_MinGW_64_bit-Debug\\ui_mainwindow.h"],"directory":"C:/Users/Chang/Desktop/灵巧手/产品版/上位机/Qt/Soft_Hand/build/Desktop_Qt_6_5_3_MinGW_64_bit-Debug/.qtc_clangd","file":"C:/Users/Chang/Desktop/灵巧手/产品版/上位机/Qt/Soft_Hand/build/Desktop_Qt_6_5_3_MinGW_64_bit-Debug/ui_mainwindow.h"}]